PyXB_X-1.2.6.2.data/scripts/pyxbdump
PyXB_X-1.2.6.2.data/scripts/pyxbgen
PyXB_X-1.2.6.2.data/scripts/pyxbwsdl
pyxb/__init__.py
pyxb/exceptions_.py
pyxb/binding/__init__.py
pyxb/binding/basis.py
pyxb/binding/content.py
pyxb/binding/datatypes.py
pyxb/binding/facets.py
pyxb/binding/generate.py
pyxb/binding/saxer.py
pyxb/binding/xml_.py
pyxb/bundles/__init__.py
pyxb/namespace/__init__.py
pyxb/namespace/archive.py
pyxb/namespace/builtin.py
pyxb/namespace/resolution.py
pyxb/namespace/utility.py
pyxb/utils/__init__.py
pyxb/utils/activestate.py
pyxb/utils/domutils.py
pyxb/utils/fac.py
pyxb/utils/saxdom.py
pyxb/utils/saxutils.py
pyxb/utils/six.py
pyxb/utils/templates.py
pyxb/utils/typeutils.py
pyxb/utils/unicode.py
pyxb/utils/unicode_data.py
pyxb/utils/utility.py
pyxb/utils/xmlre.py
pyxb/xmlschema/__init__.py
pyxb/xmlschema/structures.py
PyXB_X-1.2.6.2.dist-info/LICENSE
PyXB_X-1.2.6.2.dist-info/METADATA
PyXB_X-1.2.6.2.dist-info/NOTICE
PyXB_X-1.2.6.2.dist-info/WHEEL
PyXB_X-1.2.6.2.dist-info/top_level.txt
PyXB_X-1.2.6.2.dist-info/RECORD
