Metadata-Version: 2.1
Name: PyXB-X
Version: 1.2.6.2
Summary: PyXB-X ("pixbix") is a pure Python package that generates Python source code for classes that correspond to data structures defined by XMLSchema.
Home-page: http://pyxb.sourceforge.net
Author: Peter A. Bigot
Author-email: pabigot@users.sourceforge.net
License: Apache License 2.0
Classifier: Development Status :: 5 - Production/Stable
Classifier: Intended Audience :: Developers
Classifier: License :: OSI Approved :: Apache Software License
Classifier: Topic :: Software Development :: Code Generators
Classifier: Topic :: Text Processing :: Markup :: XML
Classifier: Programming Language :: Python :: 2
Classifier: Programming Language :: Python :: 2.6
Classifier: Programming Language :: Python :: 2.7
Classifier: Programming Language :: Python :: 3
Classifier: Programming Language :: Python :: 3.5
Classifier: Programming Language :: Python :: 3.6
Classifier: Programming Language :: Python :: 3.7
Classifier: Programming Language :: Python :: 3.8
Provides: PyXB
License-File: LICENSE
License-File: NOTICE
